littlefs_tools/__init__.py
littlefs_tools/littlefs_tools.py
littlefs_tools-1.1.7.dist-info/licenses/LICENSE
littlefs_tools-1.1.7.dist-info/METADATA
littlefs_tools-1.1.7.dist-info/WHEEL
littlefs_tools-1.1.7.dist-info/entry_points.txt
littlefs_tools-1.1.7.dist-info/top_level.txt
littlefs_tools-1.1.7.dist-info/RECORD
